{"uuid":"13ceb372-a760-41e4-9c86-60f5e1c493c7","children":[{"uuid":"e5f10d46-03ba-4dd1-a688-9e33efb5a8aa","kind":"FormteilContainer","children":[{"uuid":"f2bb4b69-475a-4bab-9d67-f63d8ce0b4cd","kind":"ZeileContainer","children":[{"uuid":"bb6fcce0-e9cf-41f3-b44a-f86015629c8a","kind":"Syllable","text":"Chan-","syllableType":"Normal","notes":{"spaced":[{"nonSpaced":[{"grouped":[{"uuid":"d138a758-5700-4754-9d9e-e55d3f75d96c","base":"A","octave":4,"noteType":"Normal","focus":false,"liquescent":false}]}]}]}},{"uuid":"7310ffbd-c418-492a-87ec-b88b9debbff2","kind":"Syllable","text":"con","syllableType":"Normal","notes":{"spaced":[{"nonSpaced":[{"grouped":[{"uuid":"0d40874a-50e4-4e04-90e1-cd26ff0992ee","base":"A","octave":4,"noteType":"Normal","focus":false,"liquescent":false}]}]}]}},{"uuid":"425f089f-fef8-467f-8ebd-5cb1fa90e245","kind":"Syllable","text":"re-","syllableType":"Normal","notes":{"spaced":[{"nonSpaced":[{"grouped":[{"uuid":"f3199428-aa88-407f-a326-e07b3706972a","base":"G","octave":4,"noteType":"Normal","focus":false,"liquescent":false}]}]}]}},{"uuid":"3fe60faf-15cb-4912-a78f-062941e2e832","kind":"Syllable","text":"nuoi-","syllableType":"Normal","notes":{"spaced":[{"nonSpaced":[{"grouped":[{"uuid":"bd3c2f7a-3ac4-46ba-9c6f-548b15385840","base":"A","octave":4,"noteType":"Normal","focus":false,"liquescent":false},{"uuid":"8baebf65-fc69-485f-875f-8677bcac8ad3","base":"G","octave":4,"noteType":"Normal","focus":false,"liquescent":false},{"uuid":"c8607829-987b-4a1e-911b-4619c5c87427","base":"F","octave":4,"noteType":"Normal","focus":false,"liquescent":false}]}]}]}},{"uuid":"64ac0fbb-72b8-41e7-85a5-88e243d2413b","kind":"Syllable","text":"si-","syllableType":"Normal","notes":{"spaced":[{"nonSpaced":[{"grouped":[{"uuid":"dc8716d4-5c54-4c06-9676-bf8326c4bc50","base":"E","octave":4,"noteType":"Normal","focus":false,"liquescent":false}]}]}]}},{"uuid":"acef140b-f180-4893-a356-9b12e94b004a","kind":"Syllable","text":"e","syllableType":"Normal","notes":{"spaced":[{"nonSpaced":[{"grouped":[{"uuid":"b1c43703-7294-40fe-a925-031545de0027","base":"F","octave":4,"noteType":"Normal","focus":false,"liquescent":false},{"uuid":"c7b1e788-db4e-4f02-b72e-c37224a69ef2","base":"E","octave":4,"noteType":"Normal","focus":false,"liquescent":false},{"uuid":"c94c9a8b-902b-4798-b04b-01a9c6fa18be","base":"D","octave":4,"noteType":"Normal","focus":false,"liquescent":false}]}]}]}},{"uuid":"7fe6969e-29de-46ef-9772-87732defd475","kind":"LineChange","focus":true},{"uuid":"8a801daa-2c0c-416c-9464-ec89975b180d","kind":"Syllable","text":"ne","syllableType":"Normal","notes":{"spaced":[{"nonSpaced":[{"grouped":[{"uuid":"7304363b-a25c-4aae-afce-2ab70daf6ff9","base":"A","octave":4,"noteType":"Normal","focus":false,"liquescent":false}]}]}]}},{"uuid":"6fb65dfc-2df7-4156-a738-577a5e1a6ad3","kind":"Syllable","text":"puet","syllableType":"Normal","notes":{"spaced":[{"nonSpaced":[{"grouped":[{"uuid":"f86e2ff0-2a2c-49a5-ab8a-2ae08fd5e460","base":"A","octave":4,"noteType":"Normal","focus":false,"liquescent":false}]}]}]}},{"uuid":"2586c53f-2ff5-4083-a0c0-873ffc96623e","kind":"Syllable","text":"mis","syllableType":"Normal","notes":{"spaced":[{"nonSpaced":[{"grouped":[{"uuid":"3a0dc3de-131d-470c-b42c-4331d37d96cb","base":"G","octave":4,"noteType":"Normal","focus":false,"liquescent":false}]}]}]}},{"uuid":"edfb23a1-6aa3-4077-970e-bca576dc1a28","kind":"Syllable","text":"tro-","syllableType":"Normal","notes":{"spaced":[{"nonSpaced":[{"grouped":[{"uuid":"1870e2fa-eddb-486a-848c-e722246da84e","base":"A","octave":4,"noteType":"Normal","focus":false,"liquescent":false},{"uuid":"61ea8822-06f5-4302-8125-cccd65db2d9c","base":"G","octave":4,"noteType":"Normal","focus":false,"liquescent":false},{"uuid":"281c8e5d-8d12-4730-9ba3-a82cf5b687b7","base":"F","octave":4,"noteType":"Normal","focus":false,"liquescent":false}]}]}]}},{"uuid":"3c0d4ad8-021d-4dec-9bc4-611edf2e15b6","kind":"Syllable","text":"uer·","syllableType":"Normal","notes":{"spaced":[{"nonSpaced":[{"grouped":[{"uuid":"c9082308-a841-4a91-b4c0-c3ed09f0f273","base":"E","octave":4,"noteType":"Normal","focus":false,"liquescent":false}]}]}]}},{"uuid":"1c507c21-c743-4626-bc26-d35c53061bf5","kind":"LineChange","focus":true},{"uuid":"e09a6fce-1c9e-487e-bb13-f2591feb37b2","kind":"Syllable","text":"sanz","syllableType":"Normal","notes":{"spaced":[{"nonSpaced":[{"grouped":[{"uuid":"a02fe044-a2e1-4c00-a0fd-5d86c13eebea","base":"A","octave":4,"noteType":"Normal","focus":false,"liquescent":false}]}]}]}},{"uuid":"021f4b45-0f7a-4b63-83b3-2d1c62e91acd","kind":"Syllable","text":"a-","syllableType":"Normal","notes":{"spaced":[{"nonSpaced":[{"grouped":[{"uuid":"78e67b29-e473-434e-bb0a-d09e5d3d36de","base":"A","octave":4,"noteType":"Normal","focus":false,"liquescent":false}]}]}]}},{"uuid":"74bcbc18-14fb-4be9-b1a4-4b50254cee8b","kind":"Syllable","text":"mour","syllableType":"Normal","notes":{"spaced":[{"nonSpaced":[{"grouped":[{"uuid":"095ba36c-d27d-4945-9f5c-9fcd584e1402","base":"G","octave":4,"noteType":"Normal","focus":false,"liquescent":false}]}]}]}},{"uuid":"12491abe-b921-46f4-b262-39d39cd4163b","kind":"Syllable","text":"io-","syllableType":"Normal","notes":{"spaced":[{"nonSpaced":[{"grouped":[{"uuid":"46e1a8ad-377b-4532-9e7b-0b7f8ad33ddc","base":"A","octave":4,"noteType":"Normal","focus":false,"liquescent":false},{"uuid":"23801254-d59b-46dd-ba9e-a0aa6adfa9ab","base":"G","octave":4,"noteType":"Normal","focus":false,"liquescent":false},{"uuid":"74ff3d64-d3eb-4c40-8243-cdaaeda24476","base":"F","octave":4,"noteType":"Normal","focus":false,"liquescent":false}]}]}]}},{"uuid":"02b6450a-df18-453e-aa7a-f9555cbaf975","kind":"Syllable","text":"li-","syllableType":"Normal","notes":{"spaced":[{"nonSpaced":[{"grouped":[{"uuid":"2ede20a8-7cf2-41e4-9b75-dcf66fa9262d","base":"E","octave":4,"noteType":"Normal","focus":false,"liquescent":false}]}]}]}},{"uuid":"26fcd1cc-4717-486c-82f0-1da830526931","kind":"Syllable","text":"e·","syllableType":"Normal","notes":{"spaced":[{"nonSpaced":[{"grouped":[{"uuid":"0043663e-60df-4bed-a50a-a1025429ebcb","base":"F","octave":4,"noteType":"Normal","focus":false,"liquescent":false},{"uuid":"5be92d9f-1ef6-4c48-a519-7a60d8647a7d","base":"E","octave":4,"noteType":"Normal","focus":false,"liquescent":false},{"uuid":"2c8eca19-f96f-4397-9351-426188632bb7","base":"D","octave":4,"noteType":"Normal","focus":false,"liquescent":false}]}]}]}},{"uuid":"1a0c94e7-7bb6-4d4e-9a84-cc40202d7801","kind":"LineChange","focus":true},{"uuid":"e3431d3c-2df3-47d8-a653-f8444db8ecf6","kind":"Syllable","text":"de","syllableType":"Normal","notes":{"spaced":[{"nonSpaced":[{"grouped":[{"uuid":"bdb608af-8f3b-4974-8864-a7ef2805649a","base":"A","octave":4,"noteType":"Normal","focus":false,"liquescent":false}]}]}]}},{"uuid":"7ef9dabb-a8d8-43cc-bb45-b6f63a1fd357","kind":"Syllable","text":"tant","syllableType":"Normal","notes":{"spaced":[{"nonSpaced":[{"grouped":[{"uuid":"b487262c-9d1a-40f9-9db4-bdfd08a2f15a","base":"A","octave":4,"noteType":"Normal","focus":false,"liquescent":false}]}]}]}},{"uuid":"7d9310d4-e5d3-491c-9eb0-78440d2eaf3d","kind":"Syllable","text":"mos","syllableType":"Normal","notes":{"spaced":[{"nonSpaced":[{"grouped":[{"uuid":"1628a4fe-3097-4a67-b639-6eca0c7d3316","base":"G","octave":4,"noteType":"Normal","focus":false,"liquescent":false}]}]}]}},{"uuid":"39686645-e498-4bba-89ea-ccb9d5480f2a","kind":"Syllable","text":"van-","syllableType":"Normal","notes":{"spaced":[{"nonSpaced":[{"grouped":[{"uuid":"166b141d-04c3-4e6c-bba6-018bd45d867d","base":"A","octave":4,"noteType":"Normal","focus":false,"liquescent":false},{"uuid":"9ac8ccd4-6bd9-48f3-98e2-8d03cd88c588","base":"G","octave":4,"noteType":"Normal","focus":false,"liquescent":false},{"uuid":"e4306ae7-c9f3-485b-853f-d04e18f1b3b0","base":"F","octave":4,"noteType":"Normal","focus":false,"liquescent":false}]}]}]}},{"uuid":"0a43571f-5959-4c31-be2a-220a5d35035c","kind":"Syllable","text":"ter·","syllableType":"Normal","notes":{"spaced":[{"nonSpaced":[{"grouped":[{"uuid":"4cf4f94b-3586-45b1-a526-02ce197d42c9","base":"E","octave":4,"noteType":"Normal","focus":false,"liquescent":false}]}]}]}},{"uuid":"9a4e0996-c8a1-42a5-99b7-4b3a4b1d5ade","kind":"LineChange","focus":true},{"uuid":"add4363e-ea70-483a-a365-f0186a8112ee","kind":"Syllable","text":"con-","syllableType":"Normal","notes":{"spaced":[{"nonSpaced":[{"grouped":[{"uuid":"d50cc95c-2024-43e3-9827-a3ad2dbcb519","base":"A","octave":3,"noteType":"Normal","focus":false,"liquescent":false}]}]}]}},{"uuid":"f03366b3-6da3-47ec-8e03-ea1e9f544b7f","kind":"Syllable","text":"ques","syllableType":"Normal","notes":{"spaced":[{"nonSpaced":[{"grouped":[{"uuid":"711cb440-cc9e-4cb5-abea-624f212d10d2","base":"C","octave":4,"noteType":"Normal","focus":false,"liquescent":false}]}]}]}},{"uuid":"29cf74ac-4025-4adc-abc0-51413e1d8d3e","kind":"Syllable","text":"en","syllableType":"Normal","notes":{"spaced":[{"nonSpaced":[{"grouped":[{"uuid":"00947300-a771-47c7-8f44-d51995e46018","base":"D","octave":4,"noteType":"Normal","focus":false,"liquescent":false}]}]}]}},{"uuid":"8198f344-3db9-45c0-beb6-ee506cbb26d8","kind":"Syllable","text":"ma","syllableType":"Normal","notes":{"spaced":[{"nonSpaced":[{"grouped":[{"uuid":"a44cfa73-d28b-4102-a4bb-f80860c69928","base":"F","octave":4,"noteType":"Normal","focus":false,"liquescent":false},{"uuid":"cc9df2d5-7db8-4199-be89-b0a91846fc61","base":"E","octave":4,"noteType":"Normal","focus":false,"liquescent":false}]}]}]}},{"uuid":"99bca01d-a100-446a-8182-bac251f727b0","kind":"Syllable","text":"vi-","syllableType":"Normal","notes":{"spaced":[{"nonSpaced":[{"grouped":[{"uuid":"c3fdc77c-4806-4cfc-9c68-b0551c80c51a","base":"D","octave":4,"noteType":"Normal","focus":false,"liquescent":false}]}]}]}},{"uuid":"5f7d4540-6a29-4085-a048-9e9d7b25bf22","kind":"Syllable","text":"e·","syllableType":"Normal","notes":{"spaced":[{"nonSpaced":[{"grouped":[{"uuid":"5c10bc85-fd7b-4628-9ad0-4cdbe88f6a72","base":"C","octave":4,"noteType":"Normal","focus":false,"liquescent":false}]}]}]}},{"uuid":"e54b6cb7-5db0-4a88-99a5-b773bc343399","kind":"LineChange","focus":true},{"uuid":"4b4969f9-e3d2-4934-b4d8-d9f616934776","kind":"Syllable","text":"ho-","syllableType":"Normal","notes":{"spaced":[{"nonSpaced":[{"grouped":[{"uuid":"5a553d45-3c2b-4606-9966-bd7509851d6c","base":"G","octave":4,"noteType":"Normal","focus":false,"liquescent":false}]}]}]}},{"uuid":"9888bf6c-53d2-401b-997e-9b0e5bbf9bbd","kind":"Syllable","text":"re","syllableType":"Normal","notes":{"spaced":[{"nonSpaced":[{"grouped":[{"uuid":"e019112c-e520-4a3b-9923-1f233ded610f","base":"G","octave":4,"noteType":"Normal","focus":false,"liquescent":false}]}]}]}},{"uuid":"7dedd037-cfd3-4a3e-9a84-6090fc4451ce","kind":"Syllable","text":"ne","syllableType":"Normal","notes":{"spaced":[{"nonSpaced":[{"grouped":[{"uuid":"d9fcdde9-1e9d-4f5e-b912-2620cba93cc8","base":"F","octave":4,"noteType":"Normal","focus":false,"liquescent":false},{"uuid":"e3364210-2d2f-45cf-9d3f-99bf445f7e8e","base":"E","octave":4,"noteType":"Normal","focus":false,"liquescent":false}]}]}]}},{"uuid":"116aef10-91b7-4f5e-a46c-d5ccab23940f","kind":"Syllable","text":"de-","syllableType":"Normal","notes":{"spaced":[{"nonSpaced":[{"grouped":[{"uuid":"8c3e0f8a-47c3-4df2-9dde-a6c7eb7ee549","base":"F","octave":4,"noteType":"Normal","focus":false,"liquescent":false},{"uuid":"7439524a-98c9-4fab-94b3-27c39693ccd2","base":"G","octave":4,"noteType":"Normal","focus":false,"liquescent":false}]}]}]}},{"uuid":"bb9cf01a-27a2-4275-b622-7b1bfba854b8","kind":"Syllable","text":"mi-","syllableType":"Normal","notes":{"spaced":[{"nonSpaced":[{"grouped":[{"uuid":"32b4918c-41d4-47f2-8cca-5ec180166f30","base":"A","octave":4,"noteType":"Normal","focus":false,"liquescent":false}]}]}]}},{"uuid":"f3d3a947-36ba-41a8-b063-128c6e98ef01","kind":"Syllable","text":"e·","syllableType":"Normal","notes":{"spaced":[{"nonSpaced":[{"grouped":[{"uuid":"dac636f7-98d8-43d8-8ed3-4bd56225ad0b","base":"B","octave":4,"noteType":"Flat","focus":false,"liquescent":false}]},{"grouped":[{"uuid":"8f2b3434-4fc2-474c-a058-63e870e24a02","base":"B","octave":4,"noteType":"Normal","focus":false,"liquescent":false},{"uuid":"0fdf1e4a-ca00-4599-9eab-d1985203b2ea","base":"A","octave":4,"noteType":"Normal","focus":false,"liquescent":false},{"uuid":"e779593c-cdc2-4272-a44a-e8a9898419ae","base":"G","octave":4,"noteType":"Normal","focus":false,"liquescent":false}]}]}]}},{"uuid":"3e4fb40f-1ed0-443d-8a72-abf53bfbcc92","kind":"LineChange","focus":true},{"uuid":"4dfab379-21ba-41d1-8dd1-19ee773e82aa","kind":"Syllable","text":"ne","syllableType":"Normal","notes":{"spaced":[{"nonSpaced":[{"grouped":[{"uuid":"fd61eccc-4e00-4c0b-839b-149908dc4924","base":"F","octave":4,"noteType":"Normal","focus":false,"liquescent":false}]}]}]}},{"uuid":"9108c221-ca9c-4a05-865e-8552e87cd399","kind":"Syllable","text":"sui","syllableType":"Normal","notes":{"spaced":[{"nonSpaced":[{"grouped":[{"uuid":"cd12eb37-058c-406c-83b9-ffbcaa86b7a1","base":"F","octave":4,"noteType":"Normal","focus":false,"liquescent":false},{"uuid":"10f46719-1ea4-4e95-b83f-619d9244e00c","base":"E","octave":4,"noteType":"Normal","focus":false,"liquescent":false}]}]}]}},{"uuid":"5a3734a0-4a00-448c-8d86-3227c4535b4c","kind":"Syllable","text":"sanz","syllableType":"Normal","notes":{"spaced":[{"nonSpaced":[{"grouped":[{"uuid":"55f7b744-5eba-431e-a820-4a3d4b9a79fa","base":"D","octave":4,"noteType":"Normal","focus":false,"liquescent":false}]}]}]}},{"uuid":"a959c09c-7684-42b9-9fde-3a2e3d29b120","kind":"Syllable","text":"a-","syllableType":"Normal","notes":{"spaced":[{"nonSpaced":[{"grouped":[{"uuid":"f1ed880c-98f4-44a0-846e-9b54257b7488","base":"D","octave":4,"noteType":"Normal","focus":false,"liquescent":false},{"uuid":"67801c1e-5ea3-41dc-bf82-97d53e54f7b3","base":"C","octave":4,"noteType":"Normal","focus":false,"liquescent":false}]}]}]}},{"uuid":"2f9a11c5-ac3f-4d9f-b28b-924d23746c69","kind":"Syllable","text":"mer·","syllableType":"Normal","notes":{"spaced":[{"nonSpaced":[{"grouped":[{"uuid":"41f77ab3-c697-4dd7-9b56-b238f9f68fb3","base":"D","octave":4,"noteType":"Normal","focus":false,"liquescent":false}]}]}]}},{"uuid":"5d006b8e-d096-4980-8abd-449d808b18f5","kind":"LineChange","focus":true},{"uuid":"2bbc64b0-26c5-4440-81e0-14c782ef3ce7","kind":"Syllable","text":"s'en","syllableType":"Normal","notes":{"spaced":[{"nonSpaced":[{"grouped":[{"uuid":"e85e0222-c07e-43aa-aefa-8229733ae777","base":"G","octave":4,"noteType":"Normal","focus":false,"liquescent":false}]}]}]}},{"uuid":"42d9bd81-a1c7-41d0-baa2-e53eb018bac3","kind":"Syllable","text":"doi-","syllableType":"Normal","notes":{"spaced":[{"nonSpaced":[{"grouped":[{"uuid":"78d73c51-15ff-41b0-a3b7-42d136b24e92","base":"G","octave":4,"noteType":"Normal","focus":false,"liquescent":false}]}]}]}},{"uuid":"4d492600-d887-40ba-8447-0aefeb47fb7b","kind":"Syllable","text":"uent","syllableType":"Normal","notes":{"spaced":[{"nonSpaced":[{"grouped":[{"uuid":"f676d53c-99e9-41bc-8353-00ed5c624495","base":"A","octave":4,"noteType":"Normal","focus":false,"liquescent":false}]}]}]}},{"uuid":"f9e2de94-53b8-4704-9dca-625bba0227a2","kind":"Syllable","text":"dou-","syllableType":"Normal","notes":{"spaced":[{"nonSpaced":[{"grouped":[{"uuid":"73d0cafb-c555-4f34-a53f-fcec3512b956","base":"B","octave":4,"noteType":"Flat","focus":false,"liquescent":false}]},{"grouped":[{"uuid":"9d6f75ca-47fd-4ca8-814a-61537511febb","base":"B","octave":4,"noteType":"Normal","focus":false,"liquescent":false},{"uuid":"eaa07224-49c4-4970-a218-d2e416157bab","base":"A","octave":4,"noteType":"Normal","focus":false,"liquescent":false},{"uuid":"2e2fc379-393e-4ad3-a55a-56ed0d9768ae","base":"G","octave":4,"noteType":"Normal","focus":false,"liquescent":false}]}]}]}},{"uuid":"a5edbc28-d135-4c4d-9f0f-de8c25aa8689","kind":"Syllable","text":"bler","syllableType":"Normal","notes":{"spaced":[{"nonSpaced":[{"grouped":[{"uuid":"a5f0ddbc-4d8b-465d-a32f-71e62863b058","base":"F","octave":4,"noteType":"Normal","focus":true,"liquescent":false}]}]}]}},{"uuid":"120f720f-cde2-445e-a1a3-616c3dc19e0a","kind":"LineChange","focus":true},{"uuid":"59fd1068-fdda-40f9-be34-4d7d10012921","kind":"Syllable","text":"mes","syllableType":"Normal","notes":{"spaced":[{"nonSpaced":[{"grouped":[{"uuid":"a3690e43-a21f-421b-ae1a-665490b994b5","base":"A","octave":4,"noteType":"Normal","focus":true,"liquescent":false}]}]}]}},{"uuid":"6517e315-a130-4ea5-b7bc-54646906a623","kind":"Syllable","text":"chan-","syllableType":"Normal","notes":{"spaced":[{"nonSpaced":[{"grouped":[{"uuid":"9603fe1a-d1e7-40da-957a-65d016083537","base":"C","octave":5,"noteType":"Normal","focus":false,"liquescent":false}]}]}]}},{"uuid":"416ebe56-b491-48f4-b4a9-f2119b18ee09","kind":"Syllable","text":"cons","syllableType":"Normal","notes":{"spaced":[{"nonSpaced":[{"grouped":[{"uuid":"eaf35f2c-87cf-4052-8ad9-282d07ed9761","base":"D","octave":5,"noteType":"Normal","focus":false,"liquescent":false},{"uuid":"6fae64cd-a697-4984-ac9a-c6f02be9be79","base":"C","octave":5,"noteType":"Normal","focus":true,"liquescent":true}]}]}]}},{"uuid":"1bbb2539-74b6-4330-a6f8-a2cda90526d0","kind":"Syllable","text":"en","syllableType":"Normal","notes":{"spaced":[{"nonSpaced":[{"grouped":[{"uuid":"cfd0b41b-71b1-498d-a276-4b4b01fbff6f","base":"B","octave":4,"noteType":"Flat","focus":false,"liquescent":false}]},{"grouped":[{"uuid":"22b5f563-e68e-4858-a4a4-507890adcf54","base":"B","octave":4,"noteType":"Normal","focus":false,"liquescent":false},{"uuid":"3218512f-c4ba-4809-9890-bbf1a1026a55","base":"A","octave":4,"noteType":"Normal","focus":false,"liquescent":false},{"uuid":"bf024f83-9569-45bb-9975-8c1cb9fe7f36","base":"G","octave":4,"noteType":"Normal","focus":false,"liquescent":false}]}]}]}},{"uuid":"25efb071-a17b-4add-aa38-4de4652a6557","kind":"Syllable","text":"mi-","syllableType":"Normal","notes":{"spaced":[{"nonSpaced":[{"grouped":[{"uuid":"2263ce6d-2d6d-4652-b7ca-20824f829ae6","base":"F","octave":4,"noteType":"Normal","focus":false,"liquescent":false}]}]}]}},{"uuid":"484f6d41-e1e6-4523-b22e-0b1994f211b5","kind":"Syllable","text":"gno-","syllableType":"Normal","notes":{"spaced":[{"nonSpaced":[{"grouped":[{"uuid":"9cf3992f-8bcc-4013-b4f0-252059b7c006","base":"A","octave":4,"noteType":"Normal","focus":false,"liquescent":false},{"uuid":"bcab7f6d-eeac-470f-953c-afa3df7f1053","base":"G","octave":4,"noteType":"Normal","focus":false,"liquescent":false}]}]}]}},{"uuid":"d05cf9b7-71ce-4522-b1b4-4b46a77affb8","kind":"Syllable","text":"ti-","syllableType":"Normal","notes":{"spaced":[{"nonSpaced":[{"grouped":[{"uuid":"8c09986d-e770-4c5e-a5bf-66e5d78e16de","base":"F","octave":4,"noteType":"Normal","focus":false,"liquescent":false},{"uuid":"20fa8c1e-d6ef-4312-aea1-ba96ba2ce32d","base":"E","octave":4,"noteType":"Normal","focus":false,"liquescent":false}]}]}]}},{"uuid":"0c84074a-957d-4722-9d9b-4070d5026f61","kind":"Syllable","text":"e·","syllableType":"Normal","notes":{"spaced":[{"nonSpaced":[{"grouped":[{"uuid":"48fbca8d-6512-4e98-94d8-1c4fc5bd4186","base":"F","octave":4,"noteType":"Normal","focus":false,"liquescent":false},{"uuid":"247c0efc-f2cc-4235-9485-343c343b86bb","base":"E","octave":4,"noteType":"Normal","focus":false,"liquescent":false},{"uuid":"550bfa98-8055-4afb-b6c5-22738dbff35a","base":"D","octave":4,"noteType":"Normal","focus":true,"liquescent":false}]}]}]}},{"uuid":"9947dded-7aeb-4b02-9638-dc21ccefdc00","kind":"LineChange","focus":true},{"uuid":"f58451ac-f59f-409a-988f-c8ea78f48eda","kind":"Syllable","text":"en","syllableType":"Normal","notes":{"spaced":[{"nonSpaced":[{"grouped":[{"uuid":"6507d224-a770-46ad-ad25-e6fd18457837","base":"C","octave":4,"noteType":"Normal","focus":false,"liquescent":false}]}]}]}},{"uuid":"ba47a31d-8190-4708-a6ae-a10303c18f14","kind":"Syllable","text":"sons·","syllableType":"Normal","notes":{"spaced":[{"nonSpaced":[{"grouped":[{"uuid":"5dc3fa7c-4801-4457-a89d-c218d34f3d99","base":"G","octave":4,"noteType":"Normal","focus":true,"liquescent":false}]}]}]}},{"uuid":"5ad162fc-f3a5-4e97-b7c4-dff1db684dac","kind":"Syllable","text":"et","syllableType":"Normal","notes":{"spaced":[{"nonSpaced":[{"grouped":[{"uuid":"46418739-9caf-43d4-80e6-9f3b114d2b54","base":"F","octave":4,"noteType":"Normal","focus":false,"liquescent":false}]}]}]}},{"uuid":"9b9aa891-4062-4ace-9f59-0e24efe53ee6","kind":"Syllable","text":"en","syllableType":"Normal","notes":{"spaced":[{"nonSpaced":[{"grouped":[{"uuid":"10bd85fd-3441-46b4-b80b-764e9369d57f","base":"A","octave":4,"noteType":"Normal","focus":false,"liquescent":false},{"uuid":"f4ea230a-8f97-4599-9126-62f0d5ba8c4e","base":"G","octave":4,"noteType":"Normal","focus":false,"liquescent":false}]}]}]}},{"uuid":"f5dbd185-cb9f-4999-b4be-c8dc58e55998","kind":"Syllable","text":"cour-","syllableType":"Normal","notes":{"spaced":[{"nonSpaced":[{"grouped":[{"uuid":"a39a4209-1f9f-438d-b2d4-d3eb7f91483c","base":"F","octave":4,"noteType":"Normal","focus":false,"liquescent":false}]}]}]}},{"uuid":"6ad005fe-490d-41ee-8704-019d4b68c06f","kind":"Syllable","text":"toi-","syllableType":"Normal","notes":{"spaced":[{"nonSpaced":[{"grouped":[{"uuid":"6fd717f4-fb26-4215-a3b3-e10ddfb9b801","base":"A","octave":4,"noteType":"Normal","focus":false,"liquescent":false},{"uuid":"f88aae62-5752-46c3-941a-aba10a00fcc8","base":"G","octave":4,"noteType":"Normal","focus":false,"liquescent":false}]}]}]}},{"uuid":"55370467-dc5e-4320-8bd8-c2cdfb50e034","kind":"Syllable","text":"si-","syllableType":"Normal","notes":{"spaced":[{"nonSpaced":[{"grouped":[{"uuid":"4d080348-b6c9-4db4-9bc4-6e87f089c0fa","base":"F","octave":4,"noteType":"Normal","focus":false,"liquescent":false},{"uuid":"fd4445fe-ef86-4eb6-b19b-591130cdb259","base":"E","octave":4,"noteType":"Normal","focus":false,"liquescent":false}]}]}]}},{"uuid":"f3568ceb-ebbe-4d4b-b21e-e76ad8d9d7d4","kind":"Syllable","text":"e·","syllableType":"Normal","notes":{"spaced":[{"nonSpaced":[{"grouped":[{"uuid":"bdf482c5-d6e5-46a7-806a-b5795e067cc4","base":"E","octave":4,"noteType":"Normal","focus":false,"liquescent":false},{"uuid":"a9e8602a-d555-427f-8938-d1612ecccf11","base":"D","octave":4,"noteType":"Normal","focus":true,"liquescent":false}]}]}]}}]}],"data":[{"name":"Signatur","data":""}]}],"comments":[],"documentType":"Level1","version":null,"kind":"RootContainer"}