{"uuid":"13ceb372-a760-41e4-9c86-60f5e1c493c7","children":[{"uuid":"7fb5f297-7af7-4929-9d01-13621f6d7d29","kind":"FormteilContainer","children":[{"uuid":"bc900f2c-2f81-4e49-85f5-664f1a12d599","kind":"ZeileContainer","children":[{"uuid":"fbf8d08d-326b-4dca-8815-ca26d897add9","kind":"Syllable","text":"Ie","syllableType":"Normal","notes":{"spaced":[{"nonSpaced":[{"grouped":[{"uuid":"4b2c6e90-3cab-4969-861b-131682733fe8","base":"D","liquescent":false,"noteType":"Normal","octave":5,"focus":false}]}]}]}},{"uuid":"1f113698-ec46-4b16-8ef6-a10b07bb2e3b","kind":"Syllable","text":"noi","syllableType":"Normal","notes":{"spaced":[{"nonSpaced":[{"grouped":[{"uuid":"293e710c-93cb-4c95-9504-7893cd269fe8","base":"E","liquescent":false,"noteType":"Normal","octave":5,"focus":false}]}]}]}},{"uuid":"d1c13e46-0c4f-4a6f-840f-ba33c1ee0169","kind":"Syllable","text":"pie-","syllableType":"Normal","notes":{"spaced":[{"nonSpaced":[{"grouped":[{"uuid":"4efe9255-f305-4157-ae3e-b8ad461f331d","base":"F","liquescent":false,"noteType":"Normal","octave":5,"focus":false}]}]}]}},{"uuid":"988d3d5c-f31b-4034-857e-594450bf80c2","kind":"Syllable","text":"ca","syllableType":"Normal","notes":{"spaced":[{"nonSpaced":[{"grouped":[{"uuid":"86670ce0-60d2-4248-907f-5cc0ed9dc0d4","base":"G","liquescent":false,"noteType":"Normal","octave":5,"focus":false}]}]}]}},{"uuid":"c3d81d8a-5abe-4440-ae0b-abd6e44364d4","kind":"Syllable","text":"nul","syllableType":"Normal","notes":{"spaced":[{"nonSpaced":[{"grouped":[{"uuid":"d9995911-4735-4833-9499-05dad981c32b","base":"G","liquescent":false,"noteType":"Normal","octave":5,"focus":false},{"uuid":"b82e8197-50ca-4207-8f8d-8e359150557f","base":"F","liquescent":true,"noteType":"Normal","octave":5,"focus":false}]}]}]}},{"uuid":"ab19d579-6493-43dc-8c43-7ad154602063","kind":"Syllable","text":"ta-","syllableType":"Normal","notes":{"spaced":[{"nonSpaced":[{"grouped":[{"uuid":"43d8dbe1-1e79-4372-896f-0f6e0190ac58","base":"E","liquescent":false,"noteType":"Normal","octave":5,"focus":false},{"uuid":"681e1650-e359-4c0f-935c-118932a157ea","base":"D","liquescent":false,"noteType":"Normal","octave":5,"focus":false}]}]}]}},{"uuid":"5fb20490-2ceb-43f4-9377-ee146f2cd870","kind":"Syllable","text":"lent","syllableType":"Normal","notes":{"spaced":[{"nonSpaced":[{"grouped":[{"uuid":"a6d42253-34dd-4074-a5a3-677cf9de64fa","base":"B","liquescent":false,"noteType":"Normal","octave":4,"focus":false}]}]}]}},{"uuid":"811ead4e-faa1-49bd-8027-2f7e0c3fc2ba","kind":"Syllable","text":"de","syllableType":"Normal","notes":{"spaced":[{"nonSpaced":[{"grouped":[{"uuid":"b1a01f44-5964-4be3-998a-7df0745fb4c8","base":"C","liquescent":false,"noteType":"Normal","octave":5,"focus":true}]}]}]}},{"uuid":"80bb101c-4d30-40fd-afc1-d91b3fcd5325","kind":"Syllable","text":"chan-","syllableType":"Normal","notes":{"spaced":[{"nonSpaced":[{"grouped":[{"uuid":"bb7d436d-6644-4b97-a116-0c88dfe52452","base":"D","octave":5,"noteType":"Normal","focus":false,"liquescent":false},{"uuid":"2895e55c-3cbc-477d-b967-0f0ab1128ca0","base":"C","octave":5,"noteType":"Normal","focus":false,"liquescent":false},{"uuid":"152e1bc7-3788-4004-ae68-47a7f4bf39e6","base":"B","octave":4,"noteType":"Normal","focus":false,"liquescent":false},{"uuid":"223b8a2e-5216-48db-8791-7b86d74e2d8a","base":"C","octave":5,"noteType":"Normal","focus":false,"liquescent":true}]}]}]}},{"uuid":"022ca2c3-d76d-48fa-9273-1ac56d1da7e1","kind":"Syllable","text":"ter·","syllableType":"Normal","notes":{"spaced":[{"nonSpaced":[{"grouped":[{"uuid":"e4d420bb-4502-4692-957e-2f20ee5d28d8","base":"B","focus":false,"liquescent":false,"noteType":"Normal","octave":4},{"uuid":"e0937e2f-f4e8-440b-9710-75f16d5b114e","base":"A","focus":false,"liquescent":false,"noteType":"Normal","octave":4}]}]}]}},{"uuid":"0afadf0f-84b5-47c4-acb9-9e44213929fd","kind":"Syllable","text":"pour","syllableType":"Normal","notes":{"spaced":[{"nonSpaced":[{"grouped":[{"uuid":"ca49c9f9-97bd-429a-8a42-abf9d80f8f38","base":"B","liquescent":false,"noteType":"Normal","octave":4,"focus":false}]},{"grouped":[{"uuid":"05347178-9aae-4359-9541-6aedff3ca083","base":"B","liquescent":false,"noteType":"Normal","octave":4,"focus":false},{"uuid":"cd8f8e46-e29d-488e-8342-e0dd00faff84","base":"A","liquescent":true,"noteType":"Normal","octave":4,"focus":false}]}]}]}},{"uuid":"a70e7e02-9505-48e8-8698-028f114dc620","kind":"Syllable","text":"ce","syllableType":"Normal","notes":{"spaced":[{"nonSpaced":[{"grouped":[{"uuid":"dda3be21-a376-4e24-9c67-1a2bd4263259","base":"A","liquescent":false,"noteType":"Normal","octave":4,"focus":false},{"uuid":"d4a38eba-8c5c-499b-b13f-b8ff026f1d51","base":"F","liquescent":false,"noteType":"Normal","octave":4,"focus":false}]}]}]}},{"uuid":"782310ea-3317-436a-bc6d-a58e1427baf7","kind":"Syllable","text":"ni","syllableType":"Normal","notes":{"spaced":[{"nonSpaced":[{"grouped":[{"uuid":"e48a6dd8-38d1-464f-b093-4ba30f2d2e40","base":"G","liquescent":false,"noteType":"Normal","octave":4,"focus":false},{"uuid":"a3c22348-ec2b-486e-bfe5-0cd72f652c9c","base":"A","liquescent":false,"noteType":"Normal","octave":4,"focus":false}]}]}]}},{"uuid":"cd15231d-f75a-4d42-b720-aa3f81c89e4d","kind":"Syllable","text":"vueill","syllableType":"Normal","notes":{"spaced":[{"nonSpaced":[{"grouped":[{"uuid":"dc972297-a24a-4983-a608-84d2117130f2","base":"B","liquescent":false,"noteType":"Normal","octave":4,"focus":true}]}]}]}},{"uuid":"8ca2c012-58ec-4b56-bedb-fdb03fa15ec5","kind":"Syllable","text":"me-","syllableType":"Normal","notes":{"spaced":[{"nonSpaced":[{"grouped":[{"uuid":"d5e71289-2e2e-438a-853c-d19b0a910d35","base":"C","liquescent":false,"noteType":"Normal","octave":5,"focus":false}]}]}]}},{"uuid":"f3dbacda-0ba4-4004-8c9d-b214b8812d69","kind":"Syllable","text":"tre","syllableType":"Normal","notes":{"spaced":[{"nonSpaced":[{"grouped":[{"uuid":"70b9cd39-82e2-4fab-9f00-d5452b5df861","base":"D","liquescent":false,"noteType":"Normal","octave":5,"focus":false},{"uuid":"64ff5b3f-6b29-4b74-853c-3a766890de6f","base":"C","liquescent":true,"noteType":"Normal","octave":5,"focus":false}]}]}]}},{"uuid":"cde3f174-67d7-4c7b-92e0-210950afd997","kind":"Syllable","text":"m’en-","syllableType":"Normal","notes":{"spaced":[{"nonSpaced":[{"grouped":[{"uuid":"4d098319-25e2-40b5-8369-306fa52b749b","base":"B","liquescent":false,"noteType":"Normal","octave":4,"focus":false},{"uuid":"97e71910-1301-43be-9c93-0122991d918a","base":"A","liquescent":false,"noteType":"Normal","octave":4,"focus":false}]}]}]}},{"uuid":"624710ef-c166-493d-9896-81174601dabb","kind":"Syllable","text":"ten-","syllableType":"Normal","notes":{"spaced":[{"nonSpaced":[{"grouped":[{"uuid":"4954459a-03c6-4767-9f5b-8e730e96a829","base":"B","liquescent":false,"noteType":"Normal","octave":4,"focus":false},{"uuid":"3b695b20-d09e-45b0-8bde-9646b61319f9","base":"A","liquescent":false,"noteType":"Normal","octave":4,"focus":false}]}]}]}},{"uuid":"e3ce51f6-2774-4e56-8fe5-334d7b33cb87","kind":"Syllable","text":"ti-","syllableType":"Normal","notes":{"spaced":[{"nonSpaced":[{"grouped":[{"uuid":"5bf2703e-6187-423b-b776-e274ef0b9a41","base":"B","liquescent":false,"noteType":"Normal","octave":4,"focus":false},{"uuid":"d637c43a-0a4c-4852-b61d-6bf3ed7a0ad7","base":"A","liquescent":false,"noteType":"Normal","octave":4,"focus":false},{"uuid":"553cd225-a30a-4a7d-b5b6-bc74459e0ccb","base":"G","liquescent":false,"noteType":"Normal","octave":4,"focus":false}]}]}]}},{"uuid":"76ead4fa-06d4-4c84-b613-296c0b0b76ae","kind":"Syllable","text":"on·","syllableType":"Normal","notes":{"spaced":[{"nonSpaced":[{"grouped":[{"uuid":"65832740-e639-4e98-a76f-8365d9fb3bd2","base":"G","liquescent":false,"noteType":"Normal","octave":4,"focus":false}]}]}]}},{"uuid":"76ff69e7-87a9-4464-965a-c8ab83f977cc","kind":"Syllable","text":"a","syllableType":"Normal","notes":{"spaced":[{"nonSpaced":[{"grouped":[{"uuid":"41b4e549-66d0-4666-9b87-568d708fbbbf","base":"D","liquescent":false,"noteType":"Normal","octave":5,"focus":false}]}]}]}},{"uuid":"04b488ad-5dfd-404e-87be-6c9bc0c44b42","kind":"Syllable","text":"ciauz","syllableType":"Normal","notes":{"spaced":[{"nonSpaced":[{"grouped":[{"uuid":"46ed6aab-d561-4da3-8027-71d394bedc53","base":"E","liquescent":false,"noteType":"Normal","octave":5,"focus":false}]}]}]}},{"uuid":"65533de8-1ea3-4dda-bde3-997f0fa1e099","kind":"Syllable","text":"le","syllableType":"Normal","notes":{"spaced":[{"nonSpaced":[{"grouped":[{"uuid":"2ed3b97d-945b-4e67-b341-146f2aab884d","base":"F","liquescent":false,"noteType":"Normal","octave":5,"focus":false}]}]}]}},{"uuid":"1161fed9-6cd3-44af-a1cb-7c88da10a784","kind":"Syllable","text":"lais","syllableType":"Normal","notes":{"spaced":[{"nonSpaced":[{"grouped":[{"uuid":"9aafb8f0-9a25-4b81-85ff-ba21c2f662a8","base":"G","liquescent":false,"noteType":"Normal","octave":5,"focus":false}]}]}]}},{"uuid":"40223570-17a5-447f-ad2b-ab027ace2da3","kind":"Syllable","text":"qui","syllableType":"Normal","notes":{"spaced":[{"nonSpaced":[{"grouped":[{"uuid":"b9906487-3406-4084-9e7f-391a6a8eb853","base":"G","liquescent":false,"noteType":"Normal","octave":5,"focus":false},{"uuid":"5bd0630f-241b-45ca-87e0-69725b3d55e2","base":"F","liquescent":true,"noteType":"Normal","octave":5,"focus":false}]}]}]}},{"uuid":"8131724f-da8c-408b-9dfc-0ebc00185f3b","kind":"Syllable","text":"chan-","syllableType":"Normal","notes":{"spaced":[{"nonSpaced":[{"grouped":[{"uuid":"716e8260-943d-4743-89f4-3df68821daa6","base":"E","liquescent":false,"noteType":"Normal","octave":5,"focus":false},{"uuid":"7a1b690a-47be-4719-bde7-8a84300799c4","base":"D","liquescent":false,"noteType":"Normal","octave":5,"focus":false}]}]}]}},{"uuid":"0c7740be-93e6-4870-93f1-43986e55329c","kind":"Syllable","text":"tent","syllableType":"Normal","notes":{"spaced":[{"nonSpaced":[{"grouped":[{"uuid":"81be7cfc-fcf4-48da-a02a-5b42717063e9","base":"B","liquescent":false,"noteType":"Normal","octave":4,"focus":false}]}]}]}},{"uuid":"ba228cf2-e9af-43d4-ac35-a03a35f6d90b","kind":"Syllable","text":"sanz","syllableType":"Normal","notes":{"spaced":[{"nonSpaced":[{"grouped":[{"uuid":"a0e9c270-b77d-4b68-a8a8-cffc2288fa9d","base":"C","liquescent":false,"noteType":"Normal","octave":5,"focus":false}]}]}]}},{"uuid":"0f4abe1b-d8cc-477c-8b70-0498d83fd879","kind":"Syllable","text":"a-","syllableType":"Normal","notes":{"spaced":[{"nonSpaced":[{"grouped":[{"uuid":"e4c4f780-ea1f-4986-869e-0fd996ca6630","base":"D","liquescent":false,"noteType":"Normal","octave":5,"focus":false},{"uuid":"87e2fcb6-9931-4676-94b9-9bd117ccf79c","base":"C","liquescent":false,"noteType":"Normal","octave":5,"focus":false},{"uuid":"e4247d3f-0252-4d0d-b75f-18eeb26dac1e","base":"B","liquescent":false,"noteType":"Normal","octave":4,"focus":false},{"uuid":"675638a6-b40d-4d7e-adb7-f157db53f85d","base":"C","liquescent":true,"noteType":"Normal","octave":5,"focus":false}]}]}]}},{"uuid":"878480f1-4015-450c-8996-7bce5230b71a","kind":"Syllable","text":"mer·","syllableType":"Normal","notes":{"spaced":[{"nonSpaced":[{"grouped":[{"uuid":"fb9fec57-7006-45e2-972a-f0a190650247","base":"B","liquescent":false,"noteType":"Normal","octave":4,"focus":false},{"uuid":"efa73b48-7846-4132-b9b0-619843ed1001","base":"A","liquescent":false,"noteType":"Normal","octave":4,"focus":false}]}]}]}},{"uuid":"157116f4-6208-4018-8101-c5b87b3f8466","kind":"Syllable","text":"et","syllableType":"Normal","notes":{"spaced":[{"nonSpaced":[{"grouped":[{"uuid":"f9d6c060-200b-44f9-874a-ee8d67e1ad80","base":"B","liquescent":false,"noteType":"Normal","octave":4,"focus":false}]},{"grouped":[{"uuid":"e07cdde0-bf6c-41b6-b665-3bcc08b9735f","base":"B","liquescent":false,"noteType":"Normal","octave":4,"focus":false},{"uuid":"3665b478-e389-43d3-9bf3-deb2e7b524ff","base":"A","liquescent":true,"noteType":"Normal","octave":4,"focus":false}]}]}]}},{"uuid":"5a13bd78-4594-4ee6-b680-f8b62a3cd505","kind":"Syllable","text":"qui","syllableType":"Normal","notes":{"spaced":[{"nonSpaced":[{"grouped":[{"uuid":"39525966-e7df-4d42-8e76-343040cf9c83","base":"G","liquescent":false,"noteType":"Normal","octave":4,"focus":false},{"uuid":"116b2b32-92ef-45d1-9476-9749d806b85d","base":"F","liquescent":false,"noteType":"Normal","octave":4,"focus":false}]}]}]}},{"uuid":"f5a1365e-09fa-44f9-8b57-a42a19b998db","kind":"Syllable","text":"d’a-","syllableType":"Normal","notes":{"spaced":[{"nonSpaced":[{"grouped":[{"uuid":"bf735a20-b2fa-41da-9d22-835bb5632e12","base":"G","liquescent":false,"noteType":"Normal","octave":4,"focus":false},{"uuid":"af64d9ad-919a-4d00-afe3-68d2ecc4182f","base":"A","liquescent":false,"noteType":"Normal","octave":4,"focus":false}]}]}]}},{"uuid":"3444d132-5594-4731-90d2-172a77b600d7","kind":"Syllable","text":"mours","syllableType":"Normal","notes":{"spaced":[{"nonSpaced":[{"grouped":[{"uuid":"fded8b96-eefe-499a-afcb-f120bb6465f7","base":"B","liquescent":false,"noteType":"Normal","octave":4,"focus":false}]}]}]}},{"uuid":"2c449721-58bc-4d47-814f-d541ab58bfc8","kind":"Syllable","text":"ne","syllableType":"Normal","notes":{"spaced":[{"nonSpaced":[{"grouped":[{"uuid":"fa87d706-5b70-4c96-8698-8ac358b1ebf8","base":"C","liquescent":false,"noteType":"Normal","octave":5,"focus":false}]}]}]}},{"uuid":"fa69d0a2-812e-4801-b19c-9e3eee7636c2","kind":"Syllable","text":"se-","syllableType":"Normal","notes":{"spaced":[{"nonSpaced":[{"grouped":[{"uuid":"01bdb819-5c3a-49d6-8b6d-45651706ff5b","base":"D","liquescent":false,"noteType":"Normal","octave":5,"focus":false}]},{"grouped":[{"uuid":"d70b68c7-7fde-4cd5-a301-eace0fbefa1e","base":"D","liquescent":false,"noteType":"Normal","octave":5,"focus":false},{"uuid":"11fc2544-d033-420d-aea4-2b12e5e48e96","base":"C","liquescent":true,"noteType":"Normal","octave":5,"focus":false}]}]}]}},{"uuid":"6dfd7cd2-f76d-4ddf-b12f-b3009ed01fc0","kind":"Syllable","text":"uent","syllableType":"Normal","notes":{"spaced":[{"nonSpaced":[{"grouped":[{"uuid":"8242e716-7a70-45e5-9b8f-4f32f02c0f26","base":"B","liquescent":false,"noteType":"Normal","octave":4,"focus":false},{"uuid":"e263654c-9947-44bf-ae94-bc00f3c5fd29","base":"A","liquescent":false,"noteType":"Normal","octave":4,"focus":false}]}]}]}},{"uuid":"be1b68b0-1479-4a6c-92db-dcdea01ea4b1","kind":"Syllable","text":"que","syllableType":"Normal","notes":{"spaced":[{"nonSpaced":[{"grouped":[{"uuid":"e545a7c3-2d6e-4fef-8871-b54673e5f0b0","base":"B","liquescent":false,"noteType":"Normal","octave":4,"focus":false}]},{"grouped":[{"uuid":"c7943254-521e-4944-af68-64b2ff3aebaf","base":"B","liquescent":false,"noteType":"Normal","octave":4,"focus":false},{"uuid":"b1285a8b-9320-4304-a738-654b638b7735","base":"A","liquescent":false,"noteType":"Normal","octave":4,"focus":false}]}]}]}},{"uuid":"b8af7fc6-45f0-4e1f-af91-6a0df84dc77e","kind":"Syllable","text":"le","syllableType":"Normal","notes":{"spaced":[{"nonSpaced":[{"grouped":[{"uuid":"63f53662-a876-4e2d-891a-8554bcb3d6fc","base":"B","liquescent":false,"noteType":"Normal","octave":4,"focus":false},{"uuid":"09d0846d-26bb-4fe1-8185-4f4679c5fe52","base":"A","liquescent":false,"noteType":"Normal","octave":4,"focus":false},{"uuid":"a0385db2-e32a-46db-a449-452d47c36902","base":"G","liquescent":false,"noteType":"Normal","octave":4,"focus":false}]}]}]}},{"uuid":"343150c8-ffa4-4e6f-8c5d-f25204834163","kind":"Syllable","text":"nom·","syllableType":"Normal","notes":{"spaced":[{"nonSpaced":[{"grouped":[{"uuid":"40667995-c33b-48af-bcf4-ac019b9ed469","base":"G","liquescent":false,"noteType":"Normal","octave":4,"focus":true}]}]}]}},{"uuid":"e249a5a7-c15d-438e-ac45-964c6022712e","kind":"Syllable","text":"maiz","syllableType":"Normal","notes":{"spaced":[{"nonSpaced":[{"grouped":[{"uuid":"a606d698-5d23-4567-89de-f990c8be10b4","base":"G","liquescent":false,"noteType":"Normal","octave":4,"focus":false}]}]}]}},{"uuid":"dc3ca6d0-b766-4aeb-8738-42a601d0277a","kind":"Syllable","text":"par","syllableType":"Normal","notes":{"spaced":[{"nonSpaced":[{"grouped":[{"uuid":"d088ceef-7061-4b4e-8ab2-e42555dba264","base":"A","liquescent":false,"noteType":"Normal","octave":4,"focus":false},{"uuid":"af807f73-8423-4496-826d-39e5e78b75bb","base":"B","liquescent":false,"noteType":"Normal","octave":4,"focus":false}]}]}]}},{"uuid":"f2ae5569-22b9-49c3-bb23-28b720005246","kind":"Syllable","text":"es-","syllableType":"Normal","notes":{"spaced":[{"nonSpaced":[{"grouped":[{"uuid":"631a6e95-f2c3-4ad9-841f-2c3550d4e52e","base":"C","liquescent":false,"noteType":"Normal","octave":5,"focus":false},{"uuid":"52ef5a5e-ed73-49b2-8476-b44fc1252dc6","base":"D","liquescent":false,"noteType":"Normal","octave":5,"focus":false}]}]}]}},{"uuid":"687c7e48-abcd-42ec-88b3-2eeba5d0d9d9","kind":"Syllable","text":"fors","syllableType":"Normal","notes":{"spaced":[{"nonSpaced":[{"grouped":[{"uuid":"0ed31a6b-ad34-43a4-b8f9-550f0ebddbe5","base":"D","liquescent":false,"noteType":"Normal","octave":5,"focus":false}]}]}]}},{"uuid":"8c367eec-81d2-4a40-b477-cef9b3619bd3","kind":"Syllable","text":"fe-","syllableType":"Normal","notes":{"spaced":[{"nonSpaced":[{"grouped":[{"uuid":"92364a7f-1dfe-4a3e-9644-5e15b9c1ae53","base":"E","liquescent":false,"noteType":"Normal","octave":5,"focus":false}]}]}]}},{"uuid":"6d1ec4c1-cff8-4037-a593-7818fd55e1c2","kind":"Syllable","text":"rai","syllableType":"Normal","notes":{"spaced":[{"nonSpaced":[{"grouped":[{"uuid":"3338f719-5d7d-4c6c-9d65-7858d045bcd6","base":"F","liquescent":false,"noteType":"Normal","octave":5,"focus":false}]}]}]}},{"uuid":"65eaad5c-9b5d-443d-bd9f-c57af9cc117a","kind":"Syllable","text":"ces-","syllableType":"Normal","notes":{"spaced":[{"nonSpaced":[{"grouped":[{"uuid":"948c97bf-670c-4b3f-929a-fa6b80e6817d","base":"G","liquescent":false,"noteType":"Normal","octave":5,"focus":false},{"uuid":"993c5f34-28f6-4fb6-a691-003b76a43c60","base":"F","liquescent":true,"noteType":"Normal","octave":5,"focus":false}]}]}]}},{"uuid":"eda43ffd-4b46-42dd-aa6b-7efa4d9fd6ae","kind":"Syllable","text":"te","syllableType":"Normal","notes":{"spaced":[{"nonSpaced":[{"grouped":[{"uuid":"9e0e8761-ebc4-4ac7-8427-a20ed32c7ca2","base":"E","liquescent":false,"noteType":"Normal","octave":5,"focus":false},{"uuid":"5df591f3-6c6e-4ccf-883f-29015d6b7797","base":"D","liquescent":false,"noteType":"Normal","octave":5,"focus":false}]}]}]}},{"uuid":"b18807a6-a073-4290-bed1-8b181f57a988","kind":"Syllable","text":"chan-","syllableType":"Normal","notes":{"spaced":[{"nonSpaced":[{"grouped":[{"uuid":"0526c0d5-dee2-4095-8192-88f2695b9ea9","base":"E","liquescent":false,"noteType":"Normal","octave":5,"focus":false},{"uuid":"91b4b8a9-34f0-4139-b3e9-ad955044142c","base":"D","liquescent":false,"noteType":"Normal","octave":5,"focus":false},{"uuid":"32e8d453-ddbb-40fb-ae68-031e79473760","base":"C","liquescent":false,"noteType":"Normal","octave":5,"focus":false}]}]}]}},{"uuid":"82367c9b-bd78-402a-8013-c7c3b7b4ed94","kind":"Syllable","text":"con·","syllableType":"Normal","notes":{"spaced":[{"nonSpaced":[{"grouped":[{"uuid":"adda2b48-f0a0-49e8-8c04-fd91f9ef77a5","base":"D","liquescent":false,"noteType":"Normal","octave":5,"focus":false}]}]}]}},{"uuid":"9d74fc80-9afa-4e1f-a6b2-27a6d4ba2814","kind":"Syllable","text":"d’a-","syllableType":"Normal","notes":{"spaced":[{"nonSpaced":[{"grouped":[{"uuid":"35763c12-df1d-4a21-97e3-b071efbb5980","base":"E","liquescent":false,"noteType":"Normal","octave":5,"focus":false}]}]}]}},{"uuid":"1d6c2f80-bc3f-4bea-a188-2abbd0522a0b","kind":"Syllable","text":"uen-","syllableType":"Normal","notes":{"spaced":[{"nonSpaced":[{"grouped":[{"uuid":"7dcefc96-0af3-4730-a844-8830f08b1d9b","base":"F","liquescent":false,"noteType":"Normal","octave":5,"focus":false}]}]}]}},{"uuid":"fffe65c6-c50d-4b08-8f92-154fccca580d","kind":"Syllable","text":"ture","syllableType":"Normal","notes":{"spaced":[{"nonSpaced":[{"grouped":[{"uuid":"22b4e023-a0e3-4eff-92dc-421878753382","base":"G","liquescent":false,"noteType":"Normal","octave":5,"focus":false},{"uuid":"867df2f8-d26c-4c41-864a-693391afbd5c","base":"F","liquescent":true,"noteType":"Normal","octave":5,"focus":false}]}]}]}},{"uuid":"d59b3cad-85d9-43db-a516-51d429de5165","kind":"Syllable","text":"iert","syllableType":"Normal","notes":{"spaced":[{"nonSpaced":[{"grouped":[{"uuid":"0f5087fc-4c1a-486c-941f-b6a9361f7f7e","base":"E","octave":5,"noteType":"Normal","focus":false,"liquescent":false},{"uuid":"f77f50ab-8257-41fd-933a-34fd2c72db04","base":"D","octave":5,"noteType":"Normal","focus":false,"liquescent":false},{"uuid":"b82e8c7e-cb80-4ebf-85ac-2774209a9b15","base":"E","octave":5,"noteType":"Normal","focus":false,"liquescent":false}]}]}]}},{"uuid":"daa58ac1-ce1c-458c-b12d-34f5620ca2b4","kind":"Syllable","text":"sanz","syllableType":"Normal","notes":{"spaced":[{"nonSpaced":[{"grouped":[{"uuid":"083b36e4-f397-4307-9de7-2e2f8eeb0276","base":"F","liquescent":false,"noteType":"Normal","octave":5,"focus":false}]}]}]}},{"uuid":"f77ad460-5be6-4525-bb84-56d5e3d688ba","kind":"Syllable","text":"painne","syllableType":"Normal","notes":{"spaced":[{"nonSpaced":[{"grouped":[{"uuid":"51d0ee47-7826-49e3-9cb1-1e4f2d5fcb56","base":"E","focus":false,"liquescent":false,"noteType":"Normal","octave":5}]}]}]}},{"uuid":"c4c742eb-985b-473b-9065-0770414aa114","kind":"Syllable","text":"et","syllableType":"Normal","notes":{"spaced":[{"nonSpaced":[{"grouped":[{"uuid":"ab71d223-3826-4d71-99ad-ac0165681bfe","base":"D","octave":5,"noteType":"Normal","focus":false,"liquescent":false}]},{"grouped":[{"uuid":"b7d6fcb1-0d61-48a6-ad34-7dd2695c94f9","base":"D","octave":5,"noteType":"Normal","focus":false,"liquescent":false},{"uuid":"a713b655-4ba7-433b-993d-f4cfa2ddedd6","base":"C","octave":5,"noteType":"Normal","focus":false,"liquescent":true}]}]}]}},{"uuid":"b3152df2-90ef-420b-bba6-9fbb842b29f3","kind":"Syllable","text":"sans","syllableType":"Normal","notes":{"spaced":[{"nonSpaced":[{"grouped":[{"uuid":"3b4223c0-db3d-44dd-a33b-8759422f9258","base":"B","liquescent":false,"noteType":"Normal","octave":4,"focus":false},{"uuid":"7964fc37-1346-430b-bc1e-131d0fe7ebdf","base":"A","liquescent":false,"noteType":"Normal","octave":4,"focus":false}]}]}]}},{"uuid":"a769c1c2-2033-4db1-a41a-eb58bc6072bd","kind":"Syllable","text":"pen-","syllableType":"Normal","notes":{"spaced":[{"nonSpaced":[{"grouped":[{"uuid":"42b8cd37-4466-4f65-933c-12d076a06fe4","base":"B","liquescent":false,"noteType":"Normal","octave":4,"focus":false},{"uuid":"5092df75-2744-4085-8297-7ee84d8258cc","base":"A","liquescent":false,"noteType":"Normal","octave":4,"focus":false},{"uuid":"c38435f0-0c38-4eaf-bd3f-d6b5439ad476","base":"G","liquescent":false,"noteType":"Normal","octave":4,"focus":false}]}]}]}},{"uuid":"5acd2788-4f7c-4103-8127-686661e38c3b","kind":"Syllable","text":"ser·","syllableType":"Normal","notes":{"spaced":[{"nonSpaced":[{"grouped":[{"uuid":"c8807f64-700c-4ae4-9e73-189ab45d25ff","base":"G","liquescent":false,"noteType":"Normal","octave":4,"focus":false}]}]}]}},{"uuid":"fd351fd9-dc0d-4154-92ae-06fb7f7ba0b7","kind":"Syllable","text":"et","syllableType":"Normal","notes":{"spaced":[{"nonSpaced":[{"grouped":[{"uuid":"c67ce0a4-95bc-4051-b5a6-090f133de617","base":"B","liquescent":false,"noteType":"Normal","octave":4,"focus":false}]}]}]}},{"uuid":"dffe381b-8d34-4b03-be17-572dced014c2","kind":"Syllable","text":"sil","syllableType":"Normal","notes":{"spaced":[{"nonSpaced":[{"grouped":[{"uuid":"f46cb051-f9bd-4c1b-a10d-ae8dd17aa006","base":"D","liquescent":false,"noteType":"Normal","octave":5,"focus":false}]}]}]}},{"uuid":"b6296261-14a4-455b-a1d6-bad02e0f31a9","kind":"Syllable","text":"li","syllableType":"Normal","notes":{"spaced":[{"nonSpaced":[{"grouped":[{"uuid":"9679701e-ffd8-468f-9c23-7de0b1f2bd72","base":"E","liquescent":false,"noteType":"Normal","octave":5,"focus":false},{"uuid":"dc63ab54-2133-4f41-836a-67740e16ae01","base":"F","liquescent":false,"noteType":"Normal","octave":5,"focus":false},{"uuid":"4f7fb71a-a149-4dab-9d35-4f92649c1a61","base":"G","liquescent":false,"noteType":"Normal","octave":5,"focus":false},{"uuid":"9057e066-ffa9-4cc0-95cd-e44add112019","base":"F","liquescent":true,"noteType":"Normal","octave":5,"focus":false}]}]}]}},{"uuid":"d4dba5a3-4342-4d8f-9ba0-9a866c8d41e7","kind":"Syllable","text":"plaist","syllableType":"Normal","notes":{"spaced":[{"nonSpaced":[{"grouped":[{"uuid":"2dc4e814-7d5a-43be-991d-0e46ca4ac200","base":"E","liquescent":false,"noteType":"Normal","octave":5,"focus":false},{"uuid":"bb6e3b54-2296-46a6-a003-e23e3384b60c","base":"D","liquescent":false,"noteType":"Normal","octave":5,"focus":false}]}]}]}},{"uuid":"0c636552-9c40-4444-8588-9c884c815beb","kind":"Syllable","text":"ma","syllableType":"Normal","notes":{"spaced":[{"nonSpaced":[{"grouped":[{"uuid":"8b5c013b-2ab5-415f-bd4b-19a2f0eec47a","base":"D","liquescent":false,"noteType":"Normal","octave":5,"focus":false},{"uuid":"d326dc8a-3656-4cb0-8a87-407e40e23387","base":"C","liquescent":true,"noteType":"Normal","octave":5,"focus":false}]}]}]}},{"uuid":"9bbd9407-e944-4cca-b344-f4ed7a6258e4","kind":"Syllable","text":"da-","syllableType":"Normal","notes":{"spaced":[{"nonSpaced":[{"grouped":[{"uuid":"ee3c41ca-adda-4c5f-a562-0c833ab41353","base":"B","liquescent":false,"noteType":"Normal","octave":4,"focus":false},{"uuid":"c19d0466-c658-4209-9cd6-26b5ff1ae794","base":"A","liquescent":false,"noteType":"Normal","octave":4,"focus":false}]}]}]}},{"uuid":"c91d7230-b320-426c-8769-581920e036c4","kind":"Syllable","text":"me","syllableType":"Normal","notes":{"spaced":[{"nonSpaced":[{"grouped":[{"uuid":"31b1442f-4771-40c3-b1a1-7724b938c324","base":"B","liquescent":false,"noteType":"Normal","octave":4,"focus":false},{"uuid":"d7964b42-7d00-46a5-a757-7ad1104ebc68","base":"A","liquescent":false,"noteType":"Normal","octave":4,"focus":false},{"uuid":"384cab3a-ade5-4100-96d7-83f17b3ab477","base":"G","liquescent":false,"noteType":"Normal","octave":4,"focus":false}]}]}]}},{"uuid":"79da42c8-4981-4868-98fa-7896fa1ceb47","kind":"Syllable","text":"si","syllableType":"Normal","notes":{"spaced":[{"nonSpaced":[{"grouped":[{"uuid":"bc960d02-86f2-4338-a848-3d5c7af1c803","base":"A","liquescent":false,"noteType":"Normal","octave":4,"focus":false}]}]}]}},{"uuid":"24d16404-4ac3-46be-a339-cee98387077c","kind":"Syllable","text":"m’o-","syllableType":"Normal","notes":{"spaced":[{"nonSpaced":[{"grouped":[{"uuid":"66adb973-6154-45a3-880e-663d002d6b37","base":"B","liquescent":false,"noteType":"Normal","octave":4,"focus":false}]}]}]}},{"uuid":"cfc7372d-8859-4c92-8ab1-3058c0f2aace","kind":"Syllable","text":"ci-","syllableType":"Normal","notes":{"spaced":[{"nonSpaced":[{"grouped":[{"uuid":"9b4929f8-33d4-4f9c-94c8-4109c8b35420","base":"C","liquescent":false,"noteType":"Normal","octave":5,"focus":false},{"uuid":"de3a7b26-3492-442f-8bc3-8e18f475606c","base":"B","liquescent":false,"noteType":"Normal","octave":4,"focus":false},{"uuid":"e7d0d46e-08d4-40ef-9425-0ee545b2e057","base":"A","liquescent":false,"noteType":"Normal","octave":4,"focus":false},{"uuid":"4415a2e6-2110-496d-b6a3-f19427b6e852","base":"G","liquescent":false,"noteType":"Normal","octave":4,"focus":false}]}]}]}},{"uuid":"0d320c53-d043-4517-9087-34d511400344","kind":"Syllable","text":"e·","syllableType":"Normal","notes":{"spaced":[{"nonSpaced":[{"grouped":[{"uuid":"d5690d97-38d5-4e0c-8e66-a94959f922e5","base":"A","liquescent":false,"noteType":"Normal","octave":4,"focus":false}]}]}]}},{"uuid":"6cecdc97-b4a3-4d48-8ee4-048a75545f73","kind":"Syllable","text":"c’on-","syllableType":"Normal","notes":{"spaced":[{"nonSpaced":[{"grouped":[{"uuid":"a58ea17b-4d46-4ded-997a-7806a23a43ba","base":"F","liquescent":false,"noteType":"Normal","octave":5,"focus":false}]}]}]}},{"uuid":"82870e45-726f-4a14-a41b-176708b1f32d","kind":"Syllable","text":"ques","syllableType":"Normal","notes":{"spaced":[{"nonSpaced":[{"grouped":[{"uuid":"722e5f99-fd05-4f8b-9614-a02c4e2cd46f","base":"E","liquescent":false,"noteType":"Normal","octave":5,"focus":false},{"uuid":"1e0ef29a-1540-4791-b00d-b2f1978173ac","base":"D","liquescent":false,"noteType":"Normal","octave":5,"focus":false}]}]}]}},{"uuid":"e2a5e010-d328-42bb-9241-71651bfdbfb0","kind":"Syllable","text":"chan-","syllableType":"Normal","notes":{"spaced":[{"nonSpaced":[{"grouped":[{"uuid":"44a24d42-eba4-4c18-9b85-8240aa53b50b","base":"D","liquescent":false,"noteType":"Normal","octave":5,"focus":false}]},{"grouped":[{"uuid":"09169252-3ef7-4c9a-be66-f7ee880b7ccb","base":"D","liquescent":false,"noteType":"Normal","octave":5,"focus":false},{"uuid":"b9d5c346-57dc-4f3d-a16b-151757d05e68","base":"C","liquescent":true,"noteType":"Normal","octave":5,"focus":false}]}]}]}},{"uuid":"8ac03f20-6146-4cef-a234-e6aa68539fca","kind":"Syllable","text":"cons","syllableType":"Normal","notes":{"spaced":[{"nonSpaced":[{"grouped":[{"uuid":"fa3d026c-ebd3-4fcb-a98f-610e4b4eedc7","base":"B","liquescent":false,"noteType":"Normal","octave":4,"focus":false},{"uuid":"db34733f-96b9-4f9d-bd91-fb3213aae8c9","base":"A","liquescent":false,"noteType":"Normal","octave":4,"focus":false},{"uuid":"dac46817-09fb-46ce-b99c-2c58784f1ea6","base":"B","liquescent":false,"noteType":"Normal","octave":4,"focus":false}]}]}]}},{"uuid":"5fcf1d54-c0a8-4ae3-930f-d744f20208c2","kind":"Syllable","text":"ne","syllableType":"Normal","notes":{"spaced":[{"nonSpaced":[{"grouped":[{"uuid":"8dfc2a23-58d8-4266-890d-e77c6c524be9","base":"C","liquescent":false,"noteType":"Normal","octave":5,"focus":false}]}]}]}},{"uuid":"b23e20e8-7589-468d-ba46-ef6066847924","kind":"Syllable","text":"mi","syllableType":"Normal","notes":{"spaced":[{"nonSpaced":[{"grouped":[{"uuid":"13827638-b132-4712-a9ff-61d22846e29b","base":"B","liquescent":false,"noteType":"Normal","octave":4,"focus":false},{"uuid":"3b5c6c32-5f0a-4ec0-a25e-ea8fd879c6e0","base":"A","liquescent":false,"noteType":"Normal","octave":4,"focus":false},{"uuid":"29ff1774-c77d-4ba2-9caa-1d56003e2d7d","base":"G","liquescent":false,"noteType":"Normal","octave":4,"focus":false}]}]}]}},{"uuid":"d5d39bb9-4295-42b7-baed-123d8945c534","kind":"Syllable","text":"fi-","syllableType":"Normal","notes":{"spaced":[{"nonSpaced":[{"grouped":[{"uuid":"06589624-e180-49f1-aa74-348bc8395030","base":"F","liquescent":false,"noteType":"Normal","octave":4,"focus":false}]}]}]}},{"uuid":"3b1d0b5b-318e-4d10-bbaf-6b166987225d","kind":"Syllable","text":"rent","syllableType":"Normal","notes":{"spaced":[{"nonSpaced":[{"grouped":[{"uuid":"973525dd-bcd0-4556-8d74-350ec85c7573","base":"G","liquescent":false,"noteType":"Normal","octave":4,"focus":false}]}]}]}},{"uuid":"4a671a63-a27c-46c4-bf34-e9724f312be1","kind":"Syllable","text":"a-","syllableType":"Normal","notes":{"spaced":[{"nonSpaced":[{"grouped":[{"uuid":"49f4e2ec-eafe-436d-9049-a4bcdd5b3bff","base":"A","liquescent":false,"noteType":"Normal","octave":4,"focus":false},{"uuid":"e43f7302-cc00-4dd6-8459-ab553bb54e10","base":"B","liquescent":false,"noteType":"Normal","octave":4,"focus":false}]}]}]}},{"uuid":"2cd1452c-13f9-45e6-8f7a-6951d3f990e7","kind":"Syllable","text":"i-","syllableType":"Normal","notes":{"spaced":[{"nonSpaced":[{"grouped":[{"uuid":"20ee286d-62c1-415c-b172-fd7bbd2fea0d","base":"C","liquescent":false,"noteType":"Normal","octave":5,"focus":false},{"uuid":"cb7524b5-b6d4-4daf-9083-472ecf8fe808","base":"B","liquescent":false,"noteType":"Normal","octave":4,"focus":false}]},{"grouped":[{"uuid":"3d759eda-faa1-45ed-97bf-eeeb83dfabb5","base":"B","liquescent":false,"noteType":"Normal","octave":4,"focus":false},{"uuid":"09b4f51d-b483-49df-93af-0f06811ef025","base":"A","liquescent":true,"noteType":"Normal","octave":4,"focus":false}]}]}]}},{"uuid":"b4d43cfe-7083-4422-b8ac-ae26cb3ee3a0","kind":"Syllable","text":"e","syllableType":"Normal","notes":{"spaced":[{"nonSpaced":[{"grouped":[{"uuid":"4e251b68-0f2a-42c7-81f0-f146d0264c56","base":"A","liquescent":false,"noteType":"Normal","octave":4,"focus":false},{"uuid":"ced85e43-297b-4897-9f76-4bf514bc73f7","base":"G","liquescent":false,"noteType":"Normal","octave":4,"focus":true}]}]}]}}]}],"data":[{"name":"Signatur","data":""}]}],"comments":[],"documentType":"Level1","version":null,"kind":"RootContainer"}